covid19/__init__.py
covid19/cli/__init__.py
covid19/cli/__main__.py
covid19/cli/_examine_dataset.py
covid19/cli/_generate_dataset.py
covid19/cli/_test.py
covid19/cli/_train.py
covid19/cli/_utils.py
covid19/datasets/__init__.py
covid19/datasets/_covidx.py
covid19/datasets/_ham10000.py
covid19/datasets/_image.py
covid19/datasets/_utils.py
covid19/explainers/__init__.py
covid19/explainers/_explainer.py
covid19/explainers/_gradcam.py
covid19/explainers/_ig.py
covid19/explainers/_utils.py
covid19/gui/__init__.py
covid19/gui/__main__.py
covid19/gui/_client.py
covid19/gui/_resource_rc.py
covid19/gui/_ui_client.py
covid19/layers/__init__.py
covid19/layers/_pepx.py
covid19/layers/_rescaling.py
covid19/metrics/__init__.py
covid19/metrics/_imbalanced.py
covid19/metrics/_training.py
covid19/models/__init__.py
covid19/models/_covidnet.py
covid19/models/_model.py
covid19/models/_resnet50.py
covid19_detection-0.3.6.data/scripts/install.sh
covid19_detection-0.3.6.data/scripts/plot_tensorboard_logs.py
covid19_detection-0.3.6.dist-info/LICENSE
covid19_detection-0.3.6.dist-info/METADATA
covid19_detection-0.3.6.dist-info/WHEEL
covid19_detection-0.3.6.dist-info/entry_points.txt
covid19_detection-0.3.6.dist-info/top_level.txt
covid19_detection-0.3.6.dist-info/RECORD
