Metadata-Version: 2.1
Name: covid19-detection
Version: 0.3.6
Summary: Detection of COVID-19 from Chest X-Ray Images
Home-page: https://github.com/franco-ruggeri/dd2424-covid19-detection
Author: Franco Ruggeri, Fredrik Danielsson, Muhammad Tousif Zaman, Milan Jolić
Author-email: fruggeri@kth.se, fdaniels@kth.se, mtzaman@kth.se, jolic@kth.se
License: GPL
Platform: UNKNOWN
License-File: LICENSE
Requires-Dist: tensorflow (~=2.3.0)
Requires-Dist: tensorflow-addons (~=0.11.2)
Requires-Dist: opencv-python (~=4.4.0.42)
Requires-Dist: numpy (~=1.18.5)
Requires-Dist: pandas (~=1.1.1)
Requires-Dist: pydicom (~=2.0.0)
Requires-Dist: tqdm (~=4.48.2)
Requires-Dist: matplotlib (~=3.3.1)
Requires-Dist: sklearn (~=0.0)
Requires-Dist: scikit-learn (~=0.23.2)
Requires-Dist: seaborn (~=0.10.1)
Requires-Dist: xlrd (~=1.2.0)
Requires-Dist: scipy (~=1.4.1)
Requires-Dist: pyside6 (~=6.1.0)
